mld_normal/__init__.py
mld_normal/dinamic_linear_model.py
mld_normal/gibbs_sampler.py
mld_normal/simulator_linear_model.py
mld_normal_yan_werneck_tcc-0.0.14.dist-info/LICENSE
mld_normal_yan_werneck_tcc-0.0.14.dist-info/METADATA
mld_normal_yan_werneck_tcc-0.0.14.dist-info/WHEEL
mld_normal_yan_werneck_tcc-0.0.14.dist-info/top_level.txt
mld_normal_yan_werneck_tcc-0.0.14.dist-info/RECORD
