Metadata-Version: 2.1
Name: mld-normal-yan-werneck-tcc
Version: 0.0.14
Summary: Dinamic Linear Model With Normal Distribution
Home-page: https://github.com/yanwerneck/tcc
Author: Yan Werneck
Author-email: yan_werneck@yahoo.com.br
License: MIT
Platform: UNKNOWN
Requires-Python: >=3.6
Requires-Dist: numpy (==1.18.1)
Requires-Dist: scipy (==1.4.1)
